cron_utils/__init__.py
cron_utils/cron_utils.py
cron_utils-0.0.0.dist-info/METADATA
cron_utils-0.0.0.dist-info/WHEEL
cron_utils-0.0.0.dist-info/top_level.txt
cron_utils-0.0.0.dist-info/RECORD
